a2amcp/__init__.py
a2amcp/core.py
a2amcp/prompt.py
a2amcp/py.typed
a2amcp_sdk-0.1.4.dist-info/licenses/LICENSE
a2amcp_sdk-0.1.4.dist-info/METADATA
a2amcp_sdk-0.1.4.dist-info/WHEEL
a2amcp_sdk-0.1.4.dist-info/top_level.txt
a2amcp_sdk-0.1.4.dist-info/RECORD
