Metadata-Version: 2.4
Name: a2amcp-sdk
Version: 0.1.4
Summary: Python SDK for A2AMCP - Agent-to-Agent communication via Model Context Protocol
Home-page: https://github.com/webdevtodayjason/A2AMCP
Author: Jason
Author-email: 
License: MIT
Project-URL: Bug Tracker, https://github.com/webdevtodayjason/A2AMCP/issues
Project-URL: Documentation, https://github.com/webdevtodayjason/A2AMCP/blob/main/docs/API_REFERENCE.md
Project-URL: Source Code, https://github.com/webdevtodayjason/A2AMCP
Keywords: mcp ai agents communication orchestration splitmind
Classifier: Development Status :: 3 - Alpha
Classifier: Intended Audience :: Developers
Classifier: Topic :: Software Development :: Libraries :: Python Modules
Classifier: Topic :: Software Development :: Build Tools
Classifier: Topic :: System :: Distributed Computing
Classifier: Operating System :: OS Independent
Classifier: Programming Language :: Python :: 3
Classifier: Programming Language :: Python :: 3.8
Classifier: Programming Language :: Python :: 3.9
Classifier: Programming Language :: Python :: 3.10
Classifier: Programming Language :: Python :: 3.11
Classifier: Programming Language :: Python :: 3.12
Requires-Python: >=3.8
License-File: LICENSE
Requires-Dist: typing-extensions>=4.0.0; python_version < "3.10"
Provides-Extra: dev
Requires-Dist: pytest>=7.0.0; extra == "dev"
Requires-Dist: pytest-asyncio>=0.21.0; extra == "dev"
Requires-Dist: black>=23.0.0; extra == "dev"
Requires-Dist: mypy>=1.0.0; extra == "dev"
Requires-Dist: flake8>=6.0.0; extra == "dev"
Requires-Dist: isort>=5.0.0; extra == "dev"
Provides-Extra: test
Requires-Dist: pytest>=7.0.0; extra == "test"
Requires-Dist: pytest-asyncio>=0.21.0; extra == "test"
Requires-Dist: pytest-cov>=4.0.0; extra == "test"
Dynamic: author
Dynamic: classifier
Dynamic: description
Dynamic: description-content-type
Dynamic: home-page
Dynamic: keywords
Dynamic: license
Dynamic: license-file
Dynamic: project-url
Dynamic: provides-extra
Dynamic: requires-dist
Dynamic: requires-python
Dynamic: summary
